{"cameraMode":{"drawMode":0,"name":"Shaded","section":"Shading Mode"},"sceneLighting":false,"audioPlay":false,"sceneViewState":{"m_AlwaysRefresh":false,"showFog":true,"showSkybox":false,"showFlares":true,"showImageEffects":true,"showParticleSystems":true,"showVisualEffectGraphs":true,"m_FxEnabled":true},"in2DMode":false,"pivot":{"x":-2.138291835784912,"y":2.243055820465088,"z":-0.7376660108566284},"rotation":{"x":0.06262188404798508,"y":0.9336042404174805,"z":-0.2022230476140976,"w":0.28910550475120547},"size":1.0141855478286744,"orthographic":false}